data_catalog_dcat_validator/__init__.py
data_catalog_dcat_validator/errors/__init__.py
data_catalog_dcat_validator/errors/exceptions.py
data_catalog_dcat_validator/models/__init__.py
data_catalog_dcat_validator/models/base_model.py
data_catalog_dcat_validator/models/contactpoint.py
data_catalog_dcat_validator/models/datapackage.py
data_catalog_dcat_validator/models/dataset.py
data_catalog_dcat_validator/models/dcat.py
data_catalog_dcat_validator/models/dcat_resource.py
data_catalog_dcat_validator/models/distribution.py
data_catalog_dcat_validator/models/publisher.py
data_catalog_dcat_validator/models/temporal.py
data_catalog_dcat_validator/validators/__init__.py
data_catalog_dcat_validator/validators/base.py
data_catalog_dcat_validator/validators/bool.py
data_catalog_dcat_validator/validators/contactpoint.py
data_catalog_dcat_validator/validators/date.py
data_catalog_dcat_validator/validators/dict.py
data_catalog_dcat_validator/validators/distributions.py
data_catalog_dcat_validator/validators/email.py
data_catalog_dcat_validator/validators/integer.py
data_catalog_dcat_validator/validators/list_of_strings.py
data_catalog_dcat_validator/validators/publisher.py
data_catalog_dcat_validator/validators/string.py
data_catalog_dcat_validator/validators/temporal.py
data_catalog_dcat_validator-0.0.6.dist-info/LICENSE
data_catalog_dcat_validator-0.0.6.dist-info/METADATA
data_catalog_dcat_validator-0.0.6.dist-info/WHEEL
data_catalog_dcat_validator-0.0.6.dist-info/top_level.txt
data_catalog_dcat_validator-0.0.6.dist-info/RECORD
