Metadata-Version: 2.1
Name: data-catalog-dcat-validator
Version: 0.0.6
Summary: Validator for value types
Home-page: UNKNOWN
Author: NAV IKT
License: MIT
Project-URL: Bug Tracker, https://github.com/navikt/data-catalog-dcat-validator
Project-URL: Documentation, https://github.com/navikt/data-catalog-dcat-validator
Project-URL: Source Code, https://github.com/navikt/data-catalog-dcat-validator
Platform: UNKNOWN
Classifier: Development Status :: 3 - Alpha
Classifier: License :: OSI Approved :: MIT License
Classifier: Programming Language :: Python :: 3.6
Classifier: Programming Language :: Python :: 3.7
Requires-Python: >=3.6
Requires-Dist: isodate (>=0.6.0)
Requires-Dist: pytest (>=4.0.2)
